{
  "updated": "2026-03-17T02:23:39.308712+00:00",
  "count": 20,
  "incidents": [
    {
      "id": "713288aed7cb",
      "account": "@GN_carreteras",
      "type": "accident",
      "highway": "Saltillo–Mty",
      "route_key": "saltillo-monterrey",
      "km": 66.0,
      "lat": 25.6385,
      "lon": -100.356,
      "resolved": true,
      "text": "#ViaLibre en #NuevoLeón tras #AccidenteVial cerca del km 066+100, en la carretera Saltillo-Monterrey. Maneje con precaución. #ViaLibre en #NuevoLeón tras #AccidenteVial cerca del km 066+100, en la carretera Saltillo-Monterrey. Maneje con precaución.",
      "link": "https://nitter.net/GN_Carreteras/status/2033730025644495068#m",
      "date": "2026-03-17T02:19:57+00:00"
    },
    {
      "id": "342b727156dc",
      "account": "@GN_carreteras",
      "type": "blockade",
      "highway": "Zac–Durango",
      "route_key": "zacatecas-durango",
      "km": 26.0,
      "lat": 22.935177,
      "lon": -102.763813,
      "resolved": true,
      "text": "#VíaLibre en #Zacatecas tras presencia de personas cerca del km 026+850, en la carretera Zacatecas-Durango. Maneje con precaución. #VíaLibre en #Zacatecas tras presencia de personas cerca del km 026+850, en la carretera Zacatecas-Durango. Maneje con precaución.",
      "link": "https://nitter.net/GN_Carreteras/status/2033712878176342131#m",
      "date": "2026-03-17T01:11:49+00:00"
    },
    {
      "id": "ee68a640ae3f",
      "account": "@GN_carreteras",
      "type": "blockade",
      "highway": "?",
      "route_key": "unknown",
      "km": 67.0,
      "lat": 23.6345,
      "lon": -102.5528,
      "resolved": false,
      "text": "#VíaLibre en #Oaxaca tras presencia de personas cerca del km 067+000, en la carretera La Ventosa-Tapanatepec. Maneje con precaución. #VíaLibre en #Oaxaca tras presencia de personas cerca del km 067+000, en la carretera La Ventosa-Tapanatepec. Maneje con precaución.",
      "link": "https://nitter.net/GN_Carreteras/status/2033705452601573851#m",
      "date": "2026-03-17T00:42:18+00:00"
    },
    {
      "id": "60605acba71d",
      "account": "@GN_carreteras",
      "type": "accident",
      "highway": "Gdl–Tepic",
      "route_key": "guadalajara-tepic",
      "km": 106.0,
      "lat": 21.1476,
      "lon": -104.21,
      "resolved": true,
      "text": "#TomePrecauciones en #Jalisco se registra cierre parcial de la circulación por #AccidenteVial cerca del km 106+500, en la carretera Guadalajara-Tepic. Atienda indicación vial. #TomePrecauciones en #Jalisco se registra cierre parcial de la circulación por #AccidenteVial cerca del ",
      "link": "https://nitter.net/GN_Carreteras/status/2033704306038169793#m",
      "date": "2026-03-17T00:37:45+00:00"
    },
    {
      "id": "05232c01abb8",
      "account": "@GN_carreteras",
      "type": "accident",
      "highway": "?",
      "route_key": "unknown",
      "km": 190.0,
      "lat": 23.6345,
      "lon": -102.5528,
      "resolved": false,
      "text": "#TomePrecauciones en #Tamaulipas se registra cierre parcial de la circulación por #AccidenteVial cerca del km 190+700, en la carretera Monterrey-Reynosa Guadalajara. Atienda indicación vial. #TomePrecauciones en #Tamaulipas se registra cierre parcial de la circulación por #Accide",
      "link": "https://nitter.net/GN_Carreteras/status/2033699172319162457#m",
      "date": "2026-03-17T00:17:21+00:00"
    },
    {
      "id": "04b56879499f",
      "account": "@GN_carreteras",
      "type": "accident",
      "highway": "Lib. Sur Qro.",
      "route_key": "libramiento-queretaro",
      "km": 80.0,
      "lat": 20.588,
      "lon": -100.39,
      "resolved": true,
      "text": "#TomePrecauciones en #Jalisco se registra cierre parcial de la circulación por #AccidenteVial cerca del km 080+800, en la carretera Libramiento Sur Guadalajara. Atienda indicación vial. #TomePrecauciones en #Jalisco se registra cierre parcial de la circulación por #AccidenteVial ",
      "link": "https://nitter.net/GN_Carreteras/status/2033680573504356750#m",
      "date": "2026-03-16T23:03:27+00:00"
    },
    {
      "id": "d97f28a22df3",
      "account": "@GN_carreteras",
      "type": "accident",
      "highway": "?",
      "route_key": "unknown",
      "km": 39.0,
      "lat": 23.6345,
      "lon": -102.5528,
      "resolved": false,
      "text": "#TomePrecauciones en #Aguascalientes se registra cierre parcial de la circulación por #AccidenteVial cerca del km 039+800, en la carretera Aguascalientes-Jalpa. Atienda indicación vial. #TomePrecauciones en #Aguascalientes se registra cierre parcial de la circulación por #Acciden",
      "link": "https://nitter.net/GN_Carreteras/status/2033675120892318000#m",
      "date": "2026-03-16T22:41:47+00:00"
    },
    {
      "id": "2f25984044c5",
      "account": "@GN_carreteras",
      "type": "accident",
      "highway": "?",
      "route_key": "unknown",
      "km": 265.0,
      "lat": 23.6345,
      "lon": -102.5528,
      "resolved": false,
      "text": "#TomePrecauciones en #Colima se registra cierre parcial de la circulación por #AccidenteVial cerca del km 265+500, en la carretera Acalpican-Manzanillo. Atienda indicación vial. #TomePrecauciones en #Colima se registra cierre parcial de la circulación por #AccidenteVial cerca del",
      "link": "https://nitter.net/GN_Carreteras/status/2033673366406656424#m",
      "date": "2026-03-16T22:34:49+00:00"
    },
    {
      "id": "3ddafebcd72a",
      "account": "@GN_carreteras",
      "type": "accident",
      "highway": "Puebla–Córdoba",
      "route_key": "puebla-cordoba",
      "km": 268.0,
      "lat": 18.884,
      "lon": -96.923,
      "resolved": true,
      "text": "#TomePrecauciones en #Veracruz se registra cierre parcial de la circulación por #AccidenteVial cerca del km 268+500, en la carretera Puebla-Cordoba. Atienda indicación vial. #TomePrecauciones en #Veracruz se registra cierre parcial de la circulación por #AccidenteVial cerca del k",
      "link": "https://nitter.net/GN_Carreteras/status/2033671013779546493#m",
      "date": "2026-03-16T22:25:28+00:00"
    },
    {
      "id": "44e56706c000",
      "account": "@GN_carreteras",
      "type": "closure",
      "highway": "?",
      "route_key": "unknown",
      "km": 67.0,
      "lat": 23.6345,
      "lon": -102.5528,
      "resolved": false,
      "text": "#TomePrecauciones en #Oaxaca se registra cierre total de la circulación por presencia de personas, cerca del km 067+000, en la carretera La Ventosa-Tepanatepec. Pobladores permiten acceso únicamente para vehículos de emergencia. Atienda indicación vial. #TomePrecauciones en #Oaxa",
      "link": "https://nitter.net/GN_Carreteras/status/2033669149017182431#m",
      "date": "2026-03-16T22:18:03+00:00"
    },
    {
      "id": "a13afb5bd969",
      "account": "@GN_carreteras",
      "type": "accident",
      "highway": "?",
      "route_key": "unknown",
      "km": 130.0,
      "lat": 23.6345,
      "lon": -102.5528,
      "resolved": false,
      "text": "#TomePrecauciones en #Chihuahua se registra cierre parcial de la circulación por #AccidenteVial cerca del km 130+500, en la carretera Jiménez-Delicias. Atienda indicación vial. #TomePrecauciones en #Chihuahua se registra cierre parcial de la circulación por #AccidenteVial cerca d",
      "link": "https://nitter.net/GN_Carreteras/status/2033665004256288973#m",
      "date": "2026-03-16T22:01:35+00:00"
    },
    {
      "id": "73e15f93ed1b",
      "account": "@GN_carreteras",
      "type": "accident",
      "highway": "?",
      "route_key": "unknown",
      "km": 213.0,
      "lat": 23.6345,
      "lon": -102.5528,
      "resolved": false,
      "text": "#TomePrecauciones en #Veracruz se registra cierre parcial de la circulación por #AccidenteVial cerca del km 213+000, en la carretera Tulancingo-Tihuatlán. Atienda indicación vial. #TomePrecauciones en #Veracruz se registra cierre parcial de la circulación por #AccidenteVial cerca",
      "link": "https://nitter.net/GN_Carreteras/status/2033663667128922614#m",
      "date": "2026-03-16T21:56:16+00:00"
    },
    {
      "id": "27a409bbc22c",
      "account": "@GN_carreteras",
      "type": "accident",
      "highway": "Méx–Puebla",
      "route_key": "mexico-puebla",
      "km": 52.0,
      "lat": 19.176667,
      "lon": -98.544,
      "resolved": true,
      "text": "#TomePrecauciones en #EdoMéx se registra cierre parcial de la circulación por #AccidenteVial cerca del km 052+800, en la carretera México-Puebla. Atienda indicación vial. #TomePrecauciones en #EdoMéx se registra cierre parcial de la circulación por #AccidenteVial cerca del km 052",
      "link": "https://nitter.net/GN_Carreteras/status/2033661006447071269#m",
      "date": "2026-03-16T21:45:42+00:00"
    },
    {
      "id": "3a60bfb72917",
      "account": "@GN_carreteras",
      "type": "accident",
      "highway": "?",
      "route_key": "unknown",
      "km": 48.0,
      "lat": 23.6345,
      "lon": -102.5528,
      "resolved": false,
      "text": "#TomePrecauciones en #Durango se registra cierre parcial de la circulación por #AccidenteVial cerca del km 048+300, en la carretera Durango-Villa Unión. Atienda indicación vial. #TomePrecauciones en #Durango se registra cierre parcial de la circulación por #AccidenteVial cerca de",
      "link": "https://nitter.net/GN_Carreteras/status/2033642687459479768#m",
      "date": "2026-03-16T20:32:54+00:00"
    },
    {
      "id": "50bced6724f5",
      "account": "@GN_carreteras",
      "type": "blockade",
      "highway": "?",
      "route_key": "unknown",
      "km": 67.0,
      "lat": 23.6345,
      "lon": -102.5528,
      "resolved": false,
      "text": "#VíaLibre en #Oaxaca tras presencia de personas cerca del km 067+000, en la carretera La Ventosa-Tepanatepec. Maneje con precaución. #VíaLibre en #Oaxaca tras presencia de personas cerca del km 067+000, en la carretera La Ventosa-Tepanatepec. Maneje con precaución.",
      "link": "https://nitter.net/GN_Carreteras/status/2033640762441707772#m",
      "date": "2026-03-16T20:25:15+00:00"
    },
    {
      "id": "1f965080a38c",
      "account": "@GN_carreteras",
      "type": "blockade",
      "highway": "?",
      "route_key": "unknown",
      "km": 20.0,
      "lat": 23.6345,
      "lon": -102.5528,
      "resolved": false,
      "text": "#VíaLibre en #Oaxaca tras presencia de personas cerca del km 020+200, en la carretera Oaxaca-Tehuantepec. Maneje con precaución. #VíaLibre en #Oaxaca tras presencia de personas cerca del km 020+200, en la carretera Oaxaca-Tehuantepec. Maneje con precaución.",
      "link": "https://nitter.net/GN_Carreteras/status/2033638197146603616#m",
      "date": "2026-03-16T20:15:04+00:00"
    },
    {
      "id": "a28ca53dacb1",
      "account": "@GN_carreteras",
      "type": "accident",
      "highway": "Méx–Querétaro",
      "route_key": "mexico-queretaro",
      "km": 202.0,
      "lat": 20.588,
      "lon": -100.39,
      "resolved": true,
      "text": "#TomePrecauciones en #Querétaro se registra cierre parcial de la circulación por #AccidenteVial cerca del km 202+200, en la carretera México-Querétaro. Atienda indicación vial. #TomePrecauciones en #Querétaro se registra cierre parcial de la circulación por #AccidenteVial cerca d",
      "link": "https://nitter.net/GN_Carreteras/status/2033624205560844586#m",
      "date": "2026-03-16T19:19:28+00:00"
    },
    {
      "id": "b1c4220e1375",
      "account": "@GN_carreteras",
      "type": "accident",
      "highway": "?",
      "route_key": "unknown",
      "km": 184.0,
      "lat": 23.6345,
      "lon": -102.5528,
      "resolved": false,
      "text": "#TomePrecauciones en #Puebla se registra cierre parcial de la circulación por #AccidenteVial cerca del km 184+400, en la carretera Tulancingo-Tihuatlán . Atienda indicación vial. #TomePrecauciones en #Puebla se registra cierre parcial de la circulación por #AccidenteVial cerca de",
      "link": "https://nitter.net/GN_Carreteras/status/2033623068300468344#m",
      "date": "2026-03-16T19:14:57+00:00"
    },
    {
      "id": "ac3e07add8af",
      "account": "@GN_carreteras",
      "type": "alert",
      "highway": "?",
      "route_key": "unknown",
      "km": 47.0,
      "lat": 23.6345,
      "lon": -102.5528,
      "resolved": false,
      "text": "R to @GN_Carreteras: Se recomienda tomar ruta alterna, en el km 047+000 a altura de la ciudad de Magdalena, Jal., para después incorporarse al km 097+000 en el entronque de Ixtlán del Río. Se recomienda tomar ruta alterna, en el km 047+000 a altura de la ciudad de Magdalena, Jal.",
      "link": "https://nitter.net/GN_Carreteras/status/2033621695332753597#m",
      "date": "2026-03-16T19:09:29+00:00"
    },
    {
      "id": "10c5bd65268f",
      "account": "@GN_carreteras",
      "type": "accident",
      "highway": "?",
      "route_key": "unknown",
      "km": 86.0,
      "lat": 23.6345,
      "lon": -102.5528,
      "resolved": false,
      "text": "#TomePrecauciones en #Nayarit se registra cierre total de la circulación por #AccidenteVial cerca del km 086+200, en la carretera Tepic-Mazatlán. Atienda indicación vial. #TomePrecauciones en #Nayarit se registra cierre total de la circulación por #AccidenteVial cerca del km 086+",
      "link": "https://nitter.net/GN_Carreteras/status/2033621680510144727#m",
      "date": "2026-03-16T19:09:26+00:00"
    }
  ]
}