{
  "updated": "2026-03-15T21:30:49.989843+00:00",
  "count": 37,
  "incidents": [
    {
      "id": "5c07d193da58",
      "account": "@capufe",
      "type": "accident",
      "highway": "Cuernavaca–Acapulco",
      "route_key": "cuernavaca-acapulco",
      "km": 309.0,
      "lat": 16.8531,
      "lon": -99.8237,
      "resolved": true,
      "text": "🟠 CIERRE PARCIAL DE CIRCULACIÓN 🟠 Autopista Cuernavaca - Acapulco, km 309, dirección Acapulco. Reducción de carriles por atención de accidente (choque de frente). Maneja con precaución. 🟠 CIERRE PARCIAL DE CIRCULACIÓN 🟠 Autopista Cuernavaca - Acapulco, km 309, dirección Acapulco.",
      "link": "https://nitter.net/CAPUFE/status/2033291041340838344#m",
      "date": "2026-03-15T21:15:35+00:00"
    },
    {
      "id": "7a54176f1e51",
      "account": "@capufe",
      "type": "accident",
      "highway": "Chih–Cd Juárez",
      "route_key": "chihuahua-juarez",
      "km": 53.0,
      "lat": 29.1518,
      "lon": -106.2578,
      "resolved": true,
      "text": "🟢 RESTABLECIMIENTO DE CIRCULACIÓN 🟢 Autopista Cd. Obregón - Guaymas, km 53, dirección Cd. Obregón. El accidente ha sido atendido. Tramo opera de manera normal. Maneja con precaución. 🚌🚙🚗🏍️ 🟢 RESTABLECIMIENTO DE CIRCULACIÓN 🟢 Autopista Cd. Obregón - Guaymas, km 53, dirección Cd. O",
      "link": "https://nitter.net/CAPUFE/status/2033284238439559301#m",
      "date": "2026-03-15T20:48:33+00:00"
    },
    {
      "id": "c473bdffaef9",
      "account": "@GN_carreteras",
      "type": "accident",
      "highway": "Méx–Toluca",
      "route_key": "mexico-toluca",
      "km": 151.0,
      "lat": 19.286,
      "lon": -99.664,
      "resolved": true,
      "text": "#TomePrecauciones en #SanLuisPotosí se registra cierre parcial de la circulación por #AccidenteVial cerca del km 151+500, en la carretera Querétaro - San Luis Potosí. Atienda indicación vial. #TomePrecauciones en #SanLuisPotosí se registra cierre parcial de la circulación por #Ac",
      "link": "https://nitter.net/GN_Carreteras/status/2033279685845512463#m",
      "date": "2026-03-15T20:30:28+00:00"
    },
    {
      "id": "42ad473c140e",
      "account": "@capufe",
      "type": "accident",
      "highway": "?",
      "route_key": "unknown",
      "km": 44.0,
      "lat": 23.6345,
      "lon": -102.5528,
      "resolved": false,
      "text": "🟠 CIERRE PARCIAL DE CIRCULACIÓN 🟠 Autopista Tehuacán - Oaxaca, km 44. Continúa circulación intermitente en ambos sentidos por atención de accidente (maniobras para el retiro de la unidad siniestrada). Maneja con precaución. 🟠 CIERRE PARCIAL DE CIRCULACIÓN 🟠 Autopista Tehuacán - O",
      "link": "https://nitter.net/CAPUFE/status/2033269422769508540#m",
      "date": "2026-03-15T19:49:41+00:00"
    },
    {
      "id": "c9012071e995",
      "account": "@capufe",
      "type": "accident",
      "highway": "?",
      "route_key": "unknown",
      "km": 35.0,
      "lat": 23.6345,
      "lon": -102.5528,
      "resolved": false,
      "text": "🟢 RESTABLECIMIENTO DE CIRCULACIÓN 🟢 #AutMéxicoPuebla, km 35, dirección CDMX. El accidente ha sido atendido. Tramo opera de manera normal. Maneja con precaución. 🚌🚙🚗🏍️ 🟢 RESTABLECIMIENTO DE CIRCULACIÓN 🟢 #AutMéxicoPuebla , km 35, dirección CDMX. El accidente ha sido atendido. Tram",
      "link": "https://nitter.net/CAPUFE/status/2033268678481899534#m",
      "date": "2026-03-15T19:46:43+00:00"
    },
    {
      "id": "88704f34b071",
      "account": "@capufe",
      "type": "accident",
      "highway": "?",
      "route_key": "unknown",
      "km": 28.0,
      "lat": 23.6345,
      "lon": -102.5528,
      "resolved": false,
      "text": "🟢 RESTABLECIMIENTO DE CIRCULACIÓN 🟢 #AutMéxicoCuernavaca, km 28, dirección Cuernavaca. El accidente ha sido atendido. Tramo opera de manera normal. Maneja con precaución. 🚌🚙🚗🏍️ 🟢 RESTABLECIMIENTO DE CIRCULACIÓN 🟢 #AutMéxicoCuernavaca , km 28, dirección Cuernavaca. El accidente ha",
      "link": "https://nitter.net/CAPUFE/status/2033268361967075348#m",
      "date": "2026-03-15T19:45:28+00:00"
    },
    {
      "id": "cf24d6a0243f",
      "account": "@GN_carreteras",
      "type": "accident",
      "highway": "Méx–Puebla",
      "route_key": "mexico-puebla",
      "km": 35.0,
      "lat": 19.233333,
      "lon": -98.68,
      "resolved": true,
      "text": "#ViaLibre en #EdoMex tras #AccidenteVial cerca del km 035+800, en la carretera México - Puebla.Maneje con precaución. #ViaLibre en #EdoMex tras #AccidenteVial cerca del km 035+800, en la carretera México - Puebla.Maneje con precaución.",
      "link": "https://nitter.net/GN_Carreteras/status/2033267684704452953#m",
      "date": "2026-03-15T19:42:46+00:00"
    },
    {
      "id": "90613e44e79e",
      "account": "@capufe",
      "type": "accident",
      "highway": "?",
      "route_key": "unknown",
      "km": 28.0,
      "lat": 23.6345,
      "lon": -102.5528,
      "resolved": false,
      "text": "🟠 CIERRE PARCIAL DE CIRCULACIÓN 🟠 #AutMéxicoCuernavaca, km 28, dirección Cuernavaca. Reducción de carriles por atención de accidente (choque contra muro central). En la zona se registra carga vehicular. Maneja con precaución. 🟠 CIERRE PARCIAL DE CIRCULACIÓN 🟠 #AutMéxicoCuernavaca",
      "link": "https://nitter.net/CAPUFE/status/2033266091183439995#m",
      "date": "2026-03-15T19:36:27+00:00"
    },
    {
      "id": "9f4ee465165e",
      "account": "@capufe",
      "type": "accident",
      "highway": "?",
      "route_key": "unknown",
      "km": 35.0,
      "lat": 23.6345,
      "lon": -102.5528,
      "resolved": false,
      "text": "🟠 CIERRE PARCIAL DE CIRCULACIÓN 🟠 #AutMéxicoPuebla, km 35, dirección CDMX. Continúa reducción de carriles por atención de accidente (labores de limpieza). En la zona se registra carga vehicular. Maneja con precaución. 🟠 CIERRE PARCIAL DE CIRCULACIÓN 🟠 #AutMéxicoPuebla , km 35, di",
      "link": "https://nitter.net/CAPUFE/status/2033261680642097265#m",
      "date": "2026-03-15T19:18:55+00:00"
    },
    {
      "id": "fb1a1c03de61",
      "account": "@capufe",
      "type": "accident",
      "highway": "Puebla–Acatzingo",
      "route_key": "puebla-acatzingo",
      "km": 141.0,
      "lat": 18.948,
      "lon": -97.45,
      "resolved": true,
      "text": "🟢 RESTABLECIMIENTO DE CIRCULACIÓN 🟢 Autopista Puebla - Acatzingo, km 141, dirección Acatzingo. El accidente ha sido atendido. Tramo opera de manera normal. Maneja con precaución. 🚌🚙🚗🏍️ 🟢 RESTABLECIMIENTO DE CIRCULACIÓN 🟢 Autopista Puebla - Acatzingo, km 141, dirección Acatzingo. ",
      "link": "https://nitter.net/CAPUFE/status/2033249529500139775#m",
      "date": "2026-03-15T18:30:38+00:00"
    },
    {
      "id": "b440f3778ae9",
      "account": "@capufe",
      "type": "accident",
      "highway": "Chih–Cd Juárez",
      "route_key": "chihuahua-juarez",
      "km": 53.0,
      "lat": 29.1518,
      "lon": -106.2578,
      "resolved": true,
      "text": "🟠 CIERRE PARCIAL DE CIRCULACIÓN 🟠 Autopista Cd. Obregón - Guaymas, km 53, dirección Cd. Obregón. Continúa circulación intermitente por atención del accidente (maniobras para el retiro de unidades siniestradas). En la zona se registra carga vehicular. Maneja con precaución. 🟠 CIER",
      "link": "https://nitter.net/CAPUFE/status/2033247081058476143#m",
      "date": "2026-03-15T18:20:54+00:00"
    },
    {
      "id": "318631796d70",
      "account": "@GN_carreteras",
      "type": "accident",
      "highway": "?",
      "route_key": "unknown",
      "km": 127.0,
      "lat": 23.6345,
      "lon": -102.5528,
      "resolved": false,
      "text": "#TomePrecauciones en #Sonora se registra cierre parcial de la circulación por #AccidenteVial cerca del km 127+050, en la carretera Sonoyta - San Luis Rio Colorado. Atienda indicación vial. #TomePrecauciones en #Sonora se registra cierre parcial de la circulación por #AccidenteVia",
      "link": "https://nitter.net/GN_Carreteras/status/2033246299886109104#m",
      "date": "2026-03-15T18:17:48+00:00"
    },
    {
      "id": "369b749adda4",
      "account": "@capufe",
      "type": "accident",
      "highway": "?",
      "route_key": "unknown",
      "km": 0.0,
      "lat": 23.6345,
      "lon": -102.5528,
      "resolved": false,
      "text": "🟢 RESTABLECIMIENTO DE CIRCULACIÓN 🟢 Autopista La Pera - Cuautla, km 0, dirección La Pera. El accidente ha sido atendido. Tramo opera de manera normal. Maneja con precaución. 🚌🚙🚗🏍️ 🟢 RESTABLECIMIENTO DE CIRCULACIÓN 🟢 Autopista La Pera - Cuautla, km 0, dirección La Pera. El acciden",
      "link": "https://nitter.net/CAPUFE/status/2033243959665766763#m",
      "date": "2026-03-15T18:08:30+00:00"
    },
    {
      "id": "7c26ce2772a8",
      "account": "@capufe",
      "type": "accident",
      "highway": "?",
      "route_key": "unknown",
      "km": 35.0,
      "lat": 23.6345,
      "lon": -102.5528,
      "resolved": false,
      "text": "🟠 CIERRE PARCIAL DE CIRCULACIÓN 🟠 #AutMéxicoPuebla, km 35, dirección CDMX. Se restablece la circulación con reducción de carriles. El personal continúa laborando en la atención del accidente (maniobras para el retiro de unidad siniestrada). En la zona se registra carga vehicular.",
      "link": "https://nitter.net/CAPUFE/status/2033240196137767073#m",
      "date": "2026-03-15T17:53:33+00:00"
    },
    {
      "id": "42cf4e16ea66",
      "account": "@capufe",
      "type": "accident",
      "highway": "?",
      "route_key": "unknown",
      "km": 0.0,
      "lat": 23.6345,
      "lon": -102.5528,
      "resolved": false,
      "text": "🟠 CIERRE PARCIAL DE CIRCULACIÓN 🟠 Autopista La Pera - Cuautla, km 0, dirección La Pera. Reducción de carriles por atención de accidente (caída de motociclista). Maneja con precaución. 🟠 CIERRE PARCIAL DE CIRCULACIÓN 🟠 Autopista La Pera - Cuautla, km 0, dirección La Pera. Reducció",
      "link": "https://nitter.net/CAPUFE/status/2033239307117350987#m",
      "date": "2026-03-15T17:50:01+00:00"
    },
    {
      "id": "9e723b4482e2",
      "account": "@capufe",
      "type": "accident",
      "highway": "Puebla–Acatzingo",
      "route_key": "puebla-acatzingo",
      "km": 141.0,
      "lat": 18.948,
      "lon": -97.45,
      "resolved": true,
      "text": "🟠 CARGA VEHICULAR 🟠 Autopista Puebla - Acatzingo, km 141, dirección Acatzingo. El accidente ha sido atendido. En la zona se registra carga vehicular. Maneja con precaución. 🟠 CARGA VEHICULAR 🟠 Autopista Puebla - Acatzingo, km 141, dirección Acatzingo. El accidente ha sido atendid",
      "link": "https://nitter.net/CAPUFE/status/2033234107749240910#m",
      "date": "2026-03-15T17:29:21+00:00"
    },
    {
      "id": "295ead1a27df",
      "account": "@GN_carreteras",
      "type": "accident",
      "highway": "?",
      "route_key": "unknown",
      "km": 44.0,
      "lat": 23.6345,
      "lon": -102.5528,
      "resolved": false,
      "text": "#Tomeprecauciones en #Puebla se registra cierre parcial de circulación por #AccidenteVial cerca del km 044+600, de la carretera Puebla - Tehuacán. Atienda indicación vial. #Tomeprecauciones en #Puebla se registra cierre parcial de circulación por #AccidenteVial cerca del km 044+6",
      "link": "https://nitter.net/GN_Carreteras/status/2033232881531670616#m",
      "date": "2026-03-15T17:24:29+00:00"
    },
    {
      "id": "fb386d1a8d04",
      "account": "@GN_carreteras",
      "type": "accident",
      "highway": "?",
      "route_key": "unknown",
      "km": 106.0,
      "lat": 23.6345,
      "lon": -102.5528,
      "resolved": false,
      "text": "#TomePrecauciones en #SanLuisPotosí se registra cierre parcial de la circulación por #AccidenteVial cerca del km 106+800, en la carretera San Luis Potosí - Matehuala. Atienda indicación vial. #TomePrecauciones en #SanLuisPotosí se registra cierre parcial de la circulación por #Ac",
      "link": "https://nitter.net/GN_Carreteras/status/2033225285395726632#m",
      "date": "2026-03-15T16:54:18+00:00"
    },
    {
      "id": "ce2ebba2eae5",
      "account": "@capufe",
      "type": "accident",
      "highway": "?",
      "route_key": "unknown",
      "km": 35.0,
      "lat": 23.6345,
      "lon": -102.5528,
      "resolved": false,
      "text": "🔴 CIERRE DE CIRCULACIÓN 🔴 #AutMéxicoPuebla, km 35, dirección CDMX. Cierre a la circulación por atención de accidente (maniobras para el retiro de tracto camión siniestrado). Toma tus precauciones. Para más información llama al 0⃣7⃣4⃣. 🔴 CIERRE DE CIRCULACIÓN 🔴 #AutMéxicoPuebla , ",
      "link": "https://nitter.net/CAPUFE/status/2033223815904248107#m",
      "date": "2026-03-15T16:48:27+00:00"
    },
    {
      "id": "a64c58398298",
      "account": "@capufe",
      "type": "accident",
      "highway": "Puebla–Acatzingo",
      "route_key": "puebla-acatzingo",
      "km": 141.0,
      "lat": 18.948,
      "lon": -97.45,
      "resolved": true,
      "text": "🟠 CIERRE PARCIAL DE CIRCULACIÓN 🟠 Autopista Puebla - Acatzingo, km 141, dirección Acatzingo. Reducción de carriles por atención de accidente (volcadura de camioneta). En la zona se registra carga vehicular. Maneja con precaución. 🟠 CIERRE PARCIAL DE CIRCULACIÓN 🟠 Autopista Puebla",
      "link": "https://nitter.net/CAPUFE/status/2033211063844458885#m",
      "date": "2026-03-15T15:57:47+00:00"
    },
    {
      "id": "30810dc2e0c4",
      "account": "@capufe",
      "type": "accident",
      "highway": "Chih–Cd Juárez",
      "route_key": "chihuahua-juarez",
      "km": 53.0,
      "lat": 29.1518,
      "lon": -106.2578,
      "resolved": true,
      "text": "🟠 CIERRE PARCIAL DE CIRCULACIÓN 🟠 Autopista Cd. Obregón - Guaymas, km 53, dirección Cd. Obregón. Circulación intermitente por atención del accidente (maniobras para el retiro de unidades siniestradas). En la zona se registra carga vehicular. Maneja con precaución. 🟠 CIERRE PARCIA",
      "link": "https://nitter.net/CAPUFE/status/2033207713623118082#m",
      "date": "2026-03-15T15:44:28+00:00"
    },
    {
      "id": "c2cbe055e67b",
      "account": "@capufe",
      "type": "closure",
      "highway": "?",
      "route_key": "unknown",
      "km": 20.0,
      "lat": 23.6345,
      "lon": -102.5528,
      "resolved": false,
      "text": "🚧 #AVISO a las personas usuarias de la autopista #MéxicoPuebla 🚧 Se realizará cierre temporal de carriles centrales en el km 20, por montaje de estructura metálica. Tome sus precauciones. 🚧 #AVISO a las personas usuarias de la autopista #MéxicoPuebla 🚧 Se realizará cierre tempora",
      "link": "https://nitter.net/CAPUFE/status/2033206510059131048#m",
      "date": "2026-03-15T15:39:41+00:00"
    },
    {
      "id": "4f21a32831cf",
      "account": "@GN_carreteras",
      "type": "accident",
      "highway": "?",
      "route_key": "unknown",
      "km": 22.0,
      "lat": 23.6345,
      "lon": -102.5528,
      "resolved": false,
      "text": "#TomePrecauciones en #Tamaulipas se registra cierre parcial de la circulación por #AccidenteVial cerca del km 022+000, en la carretera González- Llera de Canales. Atienda indicación vial. #TomePrecauciones en #Tamaulipas se registra cierre parcial de la circulación por #Accidente",
      "link": "https://nitter.net/GN_Carreteras/status/2033201766431383957#m",
      "date": "2026-03-15T15:20:50+00:00"
    },
    {
      "id": "528c0b62aae7",
      "account": "@GN_carreteras",
      "type": "accident",
      "highway": "Méx–Puebla",
      "route_key": "mexico-puebla",
      "km": 35.0,
      "lat": 19.233333,
      "lon": -98.68,
      "resolved": true,
      "text": "#TomePrecauciones en #EdoMex se registra cierre parcial de la circulación por #AccidenteVial cerca del km 035+800, en la carretera México - Puebla. Atienda indicación vial. #TomePrecauciones en #EdoMex se registra cierre parcial de la circulación por #AccidenteVial cerca del km 0",
      "link": "https://nitter.net/GN_Carreteras/status/2033192644881289477#m",
      "date": "2026-03-15T14:44:36+00:00"
    },
    {
      "id": "c7a0e965a3bb",
      "account": "@GN_carreteras",
      "type": "accident",
      "highway": "?",
      "route_key": "unknown",
      "km": 81.0,
      "lat": 23.6345,
      "lon": -102.5528,
      "resolved": false,
      "text": "#VíaLibre en #Puebla tras #AccidenteVial cerca del km 081+200, de la carretera Puebla-Huajuapan de León. Maneje con precaución. #VíaLibre en #Puebla tras #AccidenteVial cerca del km 081+200, de la carretera Puebla-Huajuapan de León. Maneje con precaución.",
      "link": "https://nitter.net/GN_Carreteras/status/2033163498675384585#m",
      "date": "2026-03-15T12:48:47+00:00"
    },
    {
      "id": "ffc994332ef0",
      "account": "@GN_carreteras",
      "type": "accident",
      "highway": "?",
      "route_key": "unknown",
      "km": 163.0,
      "lat": 23.6345,
      "lon": -102.5528,
      "resolved": false,
      "text": "#TomePrecauciones en #NuevoLeón se registra cierre parcial de la circulación por #AccidenteVial cerca del km 163+000, en la autopista Monterrey - Nuevo Laredo. Atienda indicación vial. #TomePrecauciones en #NuevoLeón se registra cierre parcial de la circulación por #AccidenteVial",
      "link": "https://nitter.net/GN_Carreteras/status/2033162724969005554#m",
      "date": "2026-03-15T12:45:42+00:00"
    },
    {
      "id": "abfb33fec070",
      "account": "@GN_carreteras",
      "type": "accident",
      "highway": "La Tinaja–Cosoleacaque",
      "route_key": "tinaja-cosoleacaque",
      "km": 163.0,
      "lat": 18.149,
      "lon": -94.448,
      "resolved": true,
      "text": "#TomePrecauciones en #Veracruz se registra cierre parcial de la circulación por #AccidenteVial cerca del km 163+000, en la carretera La Tinaja - Cosoleacaque. Atienda indicación vial. #TomePrecauciones en #Veracruz se registra cierre parcial de la circulación por #AccidenteVial c",
      "link": "https://nitter.net/GN_Carreteras/status/2033067898332123210#m",
      "date": "2026-03-15T06:28:54+00:00"
    },
    {
      "id": "9f7d013aff79",
      "account": "@GN_carreteras",
      "type": "accident",
      "highway": "?",
      "route_key": "unknown",
      "km": 64.0,
      "lat": 23.6345,
      "lon": -102.5528,
      "resolved": false,
      "text": "#TomePrecauciones en #Guanajuato se registra cierre parcial de la circulación por #AccidenteVial cerca del km 064+900, en la carretera Acámbaro - Celaya. Atienda indicación vial. #TomePrecauciones en #Guanajuato se registra cierre parcial de la circulación por #AccidenteVial cerc",
      "link": "https://nitter.net/GN_Carreteras/status/2033059847076196582#m",
      "date": "2026-03-15T05:56:54+00:00"
    },
    {
      "id": "5b73bc8c46ec",
      "account": "@GN_carreteras",
      "type": "accident",
      "highway": "Saltillo–Mty",
      "route_key": "saltillo-monterrey",
      "km": 66.0,
      "lat": 25.6385,
      "lon": -100.356,
      "resolved": true,
      "text": "#TomePrecauciones en #NuevoLeón se registra cierre parcial de la circulación por #AccidenteVial cerca del km 066+501, en la autopista Saltillo - Monterrey. Atienda indicación vial. #TomePrecauciones en #NuevoLeón se registra cierre parcial de la circulación por #AccidenteVial cer",
      "link": "https://nitter.net/GN_Carreteras/status/2033044816087416834#m",
      "date": "2026-03-15T04:57:10+00:00"
    },
    {
      "id": "694fa4f4d9a6",
      "account": "@GN_carreteras",
      "type": "accident",
      "highway": "Méx–Querétaro",
      "route_key": "mexico-queretaro",
      "km": 52.0,
      "lat": 20.0912,
      "lon": -99.3416,
      "resolved": true,
      "text": "#VíaLibre en #EdoMex tras #AccidenteVial cerca del km 052+500, de la carretera México - Querétaro. Maneje con precaución. #VíaLibre en #EdoMex tras #AccidenteVial cerca del km 052+500, de la carretera México - Querétaro. Maneje con precaución.",
      "link": "https://nitter.net/GN_Carreteras/status/2033034151209693578#m",
      "date": "2026-03-15T04:14:48+00:00"
    },
    {
      "id": "daebcc2fe97b",
      "account": "@GN_carreteras",
      "type": "accident",
      "highway": "?",
      "route_key": "unknown",
      "km": 38.0,
      "lat": 23.6345,
      "lon": -102.5528,
      "resolved": false,
      "text": "#TomePrecauciones en #Chihuahua se registra cierre parcial de la circulación por #AccidenteVial cerca del km 038+000, en la carretera Chihuahua - Madera. Atienda indicación vial. #TomePrecauciones en #Chihuahua se registra cierre parcial de la circulación por #AccidenteVial cerca",
      "link": "https://nitter.net/GN_Carreteras/status/2033030765617770927#m",
      "date": "2026-03-15T04:01:21+00:00"
    },
    {
      "id": "23698ac66b9c",
      "account": "@GN_carreteras",
      "type": "accident",
      "highway": "?",
      "route_key": "unknown",
      "km": 80.0,
      "lat": 23.6345,
      "lon": -102.5528,
      "resolved": false,
      "text": "#TomePrecauciones en #NuevoLeón se registra cierre parcial de la circulación por #AccidenteVial cerca del km 080+000, en la carretera Monterrey - Castaños. Atienda indicación vial. #TomePrecauciones en #NuevoLeón se registra cierre parcial de la circulación por #AccidenteVial cer",
      "link": "https://nitter.net/GN_Carreteras/status/2033020838069301499#m",
      "date": "2026-03-15T03:21:54+00:00"
    },
    {
      "id": "77a71f2bacf5",
      "account": "@GN_carreteras",
      "type": "accident",
      "highway": "Méx–Querétaro",
      "route_key": "mexico-queretaro",
      "km": 52.0,
      "lat": 20.0912,
      "lon": -99.3416,
      "resolved": true,
      "text": "#Tomeprecauciones en #EdoMex se registra cierre total de circulación por #AccidenteVial cerca del km 052+500, de la carretera México - Querétaro. Se orienta a la ciudadanía #rutaalterna carretera Antigua México-Querétaro. #Tomeprecauciones en #EdoMex se registra cierre total de c",
      "link": "https://nitter.net/GN_Carreteras/status/2032987007161438425#m",
      "date": "2026-03-15T01:07:28+00:00"
    },
    {
      "id": "4d7c16c83f34",
      "account": "@GN_carreteras",
      "type": "accident",
      "highway": "?",
      "route_key": "unknown",
      "km": 144.0,
      "lat": 23.6345,
      "lon": -102.5528,
      "resolved": false,
      "text": "#TomePrecauciones en #EdoMex se registra cierre parcial de la circulación por #AccidenteVial cerca del km 144+700, en la carretera Atlacomulco - Palmillas. Atienda indicación vial. #TomePrecauciones en #EdoMex se registra cierre parcial de la circulación por #AccidenteVial cerca ",
      "link": "https://nitter.net/GN_Carreteras/status/2032968714287464904#m",
      "date": "2026-03-14T23:54:46+00:00"
    },
    {
      "id": "37e095655711",
      "account": "@GN_carreteras",
      "type": "accident",
      "highway": "Méx–Cuernavaca",
      "route_key": "mexico-cuernavaca",
      "km": 5.0,
      "lat": 19.244975,
      "lon": -99.117625,
      "resolved": true,
      "text": "#TomePrecauciones en #Morelos se registra cierre parcial de la circulación por #AccidenteVial cerca del km 005+100, en la carretera México-Cuernavaca. Atienda indicación vial. #TomePrecauciones en #Morelos se registra cierre parcial de la circulación por #AccidenteVial cerca del ",
      "link": "https://nitter.net/GN_Carreteras/status/2032967527882506579#m",
      "date": "2026-03-14T23:50:04+00:00"
    },
    {
      "id": "7abefd8412aa",
      "account": "@GN_carreteras",
      "type": "accident",
      "highway": "?",
      "route_key": "unknown",
      "km": 81.0,
      "lat": 23.6345,
      "lon": -102.5528,
      "resolved": false,
      "text": "#Tomeprecauciones en #Puebla se registra cierre parcial de circulación por #AccidenteVial cerca del km 081+200, de la carretera Puebla-Huajuapan de León. Atienda indicación vial. #Tomeprecauciones en #Puebla se registra cierre parcial de circulación por #AccidenteVial cerca del k",
      "link": "https://nitter.net/GN_Carreteras/status/2032945333085352160#m",
      "date": "2026-03-14T22:21:52+00:00"
    },
    {
      "id": "fb13c5a8fda6",
      "account": "@GN_carreteras",
      "type": "accident",
      "highway": "Méx–Querétaro",
      "route_key": "mexico-queretaro",
      "km": 98.0,
      "lat": 20.3488,
      "lon": -99.8384,
      "resolved": true,
      "text": "#Tomeprecauciones en #EdoMex se registra cierre parcial de circulación por #AccidenteVial cerca del km 098+000, de la carretera México - Querétaro. Atienda indicación vial. #Tomeprecauciones en #EdoMex se registra cierre parcial de circulación por #AccidenteVial cerca del km 098+",
      "link": "https://nitter.net/GN_Carreteras/status/2032919113677394074#m",
      "date": "2026-03-14T20:37:41+00:00"
    }
  ]
}