{
  "updated": "2026-03-24T20:02:34.938225+00:00",
  "count": 34,
  "incidents": [
    {
      "id": "9d8e2a7af943",
      "account": "@GN_carreteras",
      "type": "accident",
      "highway": "La Tinaja–Cosoleacaque",
      "route_key": "tinaja-cosoleacaque",
      "km": 15.0,
      "lat": 18.275,
      "lon": -94.95625,
      "resolved": true,
      "text": "#TomePrecauciones en #Veracruz se registra total parcial de circulación por #AccidenteVial cerca del km 015+800, de la carretera Córdoba-Ent. La Tinaja. Atienda indicación vial. #TomePrecauciones en #Veracruz se registra total parcial de circulación por #AccidenteVial cerca del k",
      "link": "https://nitter.net/GN_Carreteras/status/2036533964131676555#m",
      "date": "2026-03-24T20:01:48+00:00"
    },
    {
      "id": "f1ac0641e19c",
      "account": "@GN_carreteras",
      "type": "closure",
      "highway": "?",
      "route_key": "unknown",
      "km": 1.0,
      "lat": 23.6345,
      "lon": -102.5528,
      "resolved": false,
      "text": "#TomePrecauciones en #Guerrero se registra cierre total de circulación en carriles centrales por presencia de personas cerca del km 001+300, de la carretera Chilpancingo - Acapulco, proporcionando vialidad sobre los carriles laterales. Atienda indicación vial. #TomePrecauciones e",
      "link": "https://nitter.net/GN_Carreteras/status/2036533669926506592#m",
      "date": "2026-03-24T20:00:38+00:00"
    },
    {
      "id": "5653d1dae3a7",
      "account": "@capufe",
      "type": "accident",
      "highway": "Cuernavaca–Acapulco",
      "route_key": "cuernavaca-acapulco",
      "km": 156.0,
      "lat": 17.189936,
      "lon": -99.751344,
      "resolved": true,
      "text": "🟠 CIERRE PARCIAL DE CIRCULACIÓN 🟠 Autopista Cuernavaca - Acapulco, km 156, dirección Cuernavaca. Reducción de carriles por atención de accidente (salida del camino y volcadura de camioneta). Maneja con precaución. 🟠 CIERRE PARCIAL DE CIRCULACIÓN 🟠 Autopista Cuernavaca - Acapulco,",
      "link": "https://nitter.net/CAPUFE/status/2036532068629287199#m",
      "date": "2026-03-24T19:54:16+00:00"
    },
    {
      "id": "4fa25528aba6",
      "account": "@capufe",
      "type": "accident",
      "highway": "?",
      "route_key": "unknown",
      "km": 16.0,
      "lat": 23.6345,
      "lon": -102.5528,
      "resolved": false,
      "text": "🟢 RESTABLECIMIENTO DE CIRCULACIÓN 🟢 Autopista Córdoba - Veracruz, km 16, dirección Córdoba. El accidente ha sido atendido. Tramo opera de manera normal. Maneja con precaución. 🚌🚙🚗🏍️ 🟢 RESTABLECIMIENTO DE CIRCULACIÓN 🟢 Autopista Córdoba - Veracruz, km 16, dirección Córdoba. El acc",
      "link": "https://nitter.net/CAPUFE/status/2036530355277115826#m",
      "date": "2026-03-24T19:47:28+00:00"
    },
    {
      "id": "a1bbeeda8412",
      "account": "@capufe",
      "type": "accident",
      "highway": "?",
      "route_key": "unknown",
      "km": 131.0,
      "lat": 23.6345,
      "lon": -102.5528,
      "resolved": false,
      "text": "🟢 RESTABLECIMIENTO DE CIRCULACIÓN 🟢 Autopista Gómez Palacio - Corralitos, km 131, dirección Gómez Palacio. El accidente ha sido atendido. Tramo opera de manera normal. Maneja con precaución. 🚌🚙🚗🏍️ 🟢 RESTABLECIMIENTO DE CIRCULACIÓN 🟢 Autopista Gómez Palacio - Corralitos, km 131, d",
      "link": "https://nitter.net/CAPUFE/status/2036528669905088703#m",
      "date": "2026-03-24T19:40:46+00:00"
    },
    {
      "id": "216bcd60cbaa",
      "account": "@GN_carreteras",
      "type": "accident",
      "highway": "?",
      "route_key": "unknown",
      "km": 128.0,
      "lat": 23.6345,
      "lon": -102.5528,
      "resolved": false,
      "text": "#VíaLibre en #Durango tras #AccidenteVial cerca del km 128+360, de la carretera Gómez Palacio - Jiménez. Maneje con precaución. #VíaLibre en #Durango tras #AccidenteVial cerca del km 128+360, de la carretera Gómez Palacio - Jiménez. Maneje con precaución.",
      "link": "https://nitter.net/GN_Carreteras/status/2036521479982940372#m",
      "date": "2026-03-24T19:12:12+00:00"
    },
    {
      "id": "c5fbdc70305c",
      "account": "@GN_carreteras",
      "type": "accident",
      "highway": "?",
      "route_key": "unknown",
      "km": 23.0,
      "lat": 23.6345,
      "lon": -102.5528,
      "resolved": false,
      "text": "#TomePrecauciones en #Sonora se registra cierre parcial de circulación por #AccidenteVial cerca del km 023+200, de la carretera Los Mochis – Cd. Obregón, con dirección a Cd. Obregón, Son. Atienda indicación vial. #TomePrecauciones en #Sonora se registra cierre parcial de circulac",
      "link": "https://nitter.net/GN_Carreteras/status/2036518076418511060#m",
      "date": "2026-03-24T18:58:40+00:00"
    },
    {
      "id": "ca24afedac58",
      "account": "@capufe",
      "type": "accident",
      "highway": "?",
      "route_key": "unknown",
      "km": 72.0,
      "lat": 23.6345,
      "lon": -102.5528,
      "resolved": false,
      "text": "🟢 RESTABLECIMIENTO DE CIRCULACIÓN 🟢 #AutMéxicoPuebla, km 72, dirección Puebla. El accidente ha sido atendido. Tramo opera de manera normal. Maneja con precaución. 🚌🚙🚗🏍️ 🟢 RESTABLECIMIENTO DE CIRCULACIÓN 🟢 #AutMéxicoPuebla , km 72, dirección Puebla. El accidente ha sido atendido. ",
      "link": "https://nitter.net/CAPUFE/status/2036515628152930356#m",
      "date": "2026-03-24T18:48:57+00:00"
    },
    {
      "id": "a14be43ae136",
      "account": "@capufe",
      "type": "accident",
      "highway": "?",
      "route_key": "unknown",
      "km": 77.0,
      "lat": 23.6345,
      "lon": -102.5528,
      "resolved": false,
      "text": "🟠 CIERRE PARCIAL DE CIRCULACIÓN 🟠 Autopista Córdoba - Veracruz, km 77, dirección Veracruz. Reducción de carriles por atención de accidente (choque por alcance). Circulación lenta en la zona. Maneja con precaución. 🟠 CIERRE PARCIAL DE CIRCULACIÓN 🟠 Autopista Córdoba - Veracruz, km",
      "link": "https://nitter.net/CAPUFE/status/2036514047990915207#m",
      "date": "2026-03-24T18:42:40+00:00"
    },
    {
      "id": "679ec40572c7",
      "account": "@capufe",
      "type": "accident",
      "highway": "?",
      "route_key": "unknown",
      "km": 16.0,
      "lat": 23.6345,
      "lon": -102.5528,
      "resolved": false,
      "text": "🟠 CIERRE PARCIAL DE CIRCULACIÓN 🟠 Autopista Córdoba - Veracruz, km 16, dirección Córdoba. Reducción de carriles por atención de accidente (choque contra muro central). Maneja con precaución. 🟠 CIERRE PARCIAL DE CIRCULACIÓN 🟠 Autopista Córdoba - Veracruz, km 16, dirección Córdoba.",
      "link": "https://nitter.net/CAPUFE/status/2036513851789705613#m",
      "date": "2026-03-24T18:41:53+00:00"
    },
    {
      "id": "84190246accf",
      "account": "@capufe",
      "type": "accident",
      "highway": "?",
      "route_key": "unknown",
      "km": 209.0,
      "lat": 23.6345,
      "lon": -102.5528,
      "resolved": false,
      "text": "🟠 CIERRE PARCIAL DE CIRCULACIÓN 🟠 Autopista Acatzingo - Cd. Mendoza, km 209, dirección Cd. Mendoza. Reducción de carriles por atención de accidente (maniobras para el retiro de unidad siniestrada). Maneja con precaución. 🟠 CIERRE PARCIAL DE CIRCULACIÓN 🟠 Autopista Acatzingo - Cd.",
      "link": "https://nitter.net/CAPUFE/status/2036513606318071866#m",
      "date": "2026-03-24T18:40:54+00:00"
    },
    {
      "id": "aef53ab0618f",
      "account": "@capufe",
      "type": "accident",
      "highway": "?",
      "route_key": "unknown",
      "km": 207.0,
      "lat": 23.6345,
      "lon": -102.5528,
      "resolved": false,
      "text": "🟠 CARGA VEHICULAR 🟠 #AutMéxicoQuerétaro, km 207, dirección Querétaro. Carga vehicular intensa por atención de accidente fuera de la jurisdicción a cargo de CAPUFE. Para más información llama al 088 de @GN_Carreteras. Toma tus precauciones. 🟠 CARGA VEHICULAR 🟠 #AutMéxicoQuerétaro ",
      "link": "https://nitter.net/CAPUFE/status/2036513061742219469#m",
      "date": "2026-03-24T18:38:45+00:00"
    },
    {
      "id": "358ff3931a73",
      "account": "@GN_carreteras",
      "type": "accident",
      "highway": "Puebla–Córdoba",
      "route_key": "puebla-cordoba",
      "km": 209.0,
      "lat": 18.884,
      "lon": -96.923,
      "resolved": true,
      "text": "#TomesusPrecauciones en #Puebla se registra cierre parcial de circulación por #AccidenteVial por falla mecánica, cerca del km 209+800, de la carretera Puebla-Córdoba. Atienda indicación vial. #TomesusPrecauciones en #Puebla se registra cierre parcial de circulación por #Accidente",
      "link": "https://nitter.net/GN_Carreteras/status/2036511107154653269#m",
      "date": "2026-03-24T18:30:59+00:00"
    },
    {
      "id": "9f7fa08c2433",
      "account": "@GN_carreteras",
      "type": "accident",
      "highway": "?",
      "route_key": "unknown",
      "km": 128.0,
      "lat": 23.6345,
      "lon": -102.5528,
      "resolved": false,
      "text": "#TomesusPrecauciones en #Veracruz se registra total parcial de circulación por #AccidenteVial cerca del km 128+500, de la carretera Ciudad Alemán- Sayula. Atienda indicación vial. #TomesusPrecauciones en #Veracruz se registra total parcial de circulación por #AccidenteVial cerca ",
      "link": "https://nitter.net/GN_Carreteras/status/2036510205584797974#m",
      "date": "2026-03-24T18:27:24+00:00"
    },
    {
      "id": "06718dd4ad85",
      "account": "@GN_carreteras",
      "type": "accident",
      "highway": "?",
      "route_key": "unknown",
      "km": 238.0,
      "lat": 23.6345,
      "lon": -102.5528,
      "resolved": false,
      "text": "#TomesusPrecauciones en #Veracruz se registra total parcial de circulación por #AccidenteVial cerca del km 238+200, de la carretera Posa Rica-Veracruz, proporcionando como ruta alterna el Recinto Portuario con dirección a Xalapa. Atienda indicación vial. #TomesusPrecauciones en #",
      "link": "https://nitter.net/GN_Carreteras/status/2036509130630832140#m",
      "date": "2026-03-24T18:23:07+00:00"
    },
    {
      "id": "c3e301fa6806",
      "account": "@capufe",
      "type": "closure",
      "highway": "?",
      "route_key": "unknown",
      "km": 84.0,
      "lat": 23.6345,
      "lon": -102.5528,
      "resolved": false,
      "text": "🚧 OBRAS Y LABORES DE MANTENIMIENTO 🚧 Libramiento Cuernavaca, km 84, dirección Acapulco. Cierre de carriles centrales por labores de mantenimiento. Circulación por carriles laterales. Maneja con precaución. 🚧 OBRAS Y LABORES DE MANTENIMIENTO 🚧 Libramiento Cuernavaca, km 84, direcc",
      "link": "https://nitter.net/CAPUFE/status/2036507804840702018#m",
      "date": "2026-03-24T18:17:51+00:00"
    },
    {
      "id": "0717daa8dd59",
      "account": "@GN_carreteras",
      "type": "closure",
      "highway": "Méx–Puebla",
      "route_key": "mexico-puebla",
      "km": 81.0,
      "lat": 19.099075,
      "lon": -98.324075,
      "resolved": true,
      "text": "#TomesusPrecauciones en #Puebla se registra cierre parcial de circulación por #VehículoIncendiado por falla mecánica, cerca del km 081+200, de la carretera México-Puebla. Atienda indicación vial. #TomesusPrecauciones en #Puebla se registra cierre parcial de circulación por #Vehíc",
      "link": "https://nitter.net/GN_Carreteras/status/2036505629641076850#m",
      "date": "2026-03-24T18:09:13+00:00"
    },
    {
      "id": "19a759e86497",
      "account": "@GN_carreteras",
      "type": "accident",
      "highway": "Méx–Querétaro",
      "route_key": "mexico-queretaro",
      "km": 208.0,
      "lat": 20.588,
      "lon": -100.39,
      "resolved": true,
      "text": "#TomesusPrecauciones en #Querétaro se registra cierre total de circulación por #AccidenteVial cerca del km 208+000, de la carretera México-Querétaro, se proporciona ruta alterna sobre los carriles laterales. Atienda indicación vial. #TomesusPrecauciones en #Querétaro se registra ",
      "link": "https://nitter.net/GN_Carreteras/status/2036504355889615298#m",
      "date": "2026-03-24T18:04:09+00:00"
    },
    {
      "id": "e58001e2e47c",
      "account": "@GN_carreteras",
      "type": "accident",
      "highway": "?",
      "route_key": "unknown",
      "km": 7.0,
      "lat": 23.6345,
      "lon": -102.5528,
      "resolved": false,
      "text": "#TomesusPrecauciones en #Tamaulipas se registra cierre parcial de circulación por #AccidenteVial cerca del km 007+100, de la carretera Matamoros - Reynosa. Atienda indicación vial. #TomesusPrecauciones en #Tamaulipas se registra cierre parcial de circulación por #AccidenteVial ce",
      "link": "https://nitter.net/GN_Carreteras/status/2036503866317914323#m",
      "date": "2026-03-24T18:02:12+00:00"
    },
    {
      "id": "cfd723b28520",
      "account": "@capufe",
      "type": "closure",
      "highway": "?",
      "route_key": "unknown",
      "km": 131.0,
      "lat": 23.6345,
      "lon": -102.5528,
      "resolved": false,
      "text": "🟠 CIERRE PARCIAL DE CIRCULACIÓN 🟠 Autopista Gómez Palacio - Corralitos, km 131, dirección Gómez Palacio. Se restablece la circulación con reducción de carriles. El personal de conservación continúa realizando las labores de limpieza. En la zona se registra carga vehicular. Maneja",
      "link": "https://nitter.net/CAPUFE/status/2036502568843747413#m",
      "date": "2026-03-24T17:57:03+00:00"
    },
    {
      "id": "50f4654d0071",
      "account": "@capufe",
      "type": "accident",
      "highway": "?",
      "route_key": "unknown",
      "km": 131.0,
      "lat": 23.6345,
      "lon": -102.5528,
      "resolved": false,
      "text": "🔴 CIERRE DE CIRCULACIÓN 🔴 Autopista Gómez Palacio - Corralitos, km 131, dirección Gómez Palacio. Continúa cierre a la circulación por atención del accidente. El personal de conservación realiza labores de limpieza en la zona. Toma tus precauciones. Para más información llama al 0",
      "link": "https://nitter.net/CAPUFE/status/2036499586257395875#m",
      "date": "2026-03-24T17:45:12+00:00"
    },
    {
      "id": "264754792d4c",
      "account": "@GN_carreteras",
      "type": "accident",
      "highway": "Gdl–Tepic",
      "route_key": "guadalajara-tepic",
      "km": 138.0,
      "lat": 21.2948,
      "lon": -104.53,
      "resolved": true,
      "text": "#TomesusPrecauciones en #Chiapas se registra cierre parcial de circulación por #AccidenteVial cerca del km 138+950, de la carretera Tapanatepec-Tuxtla Gutiérrez. Atienda indicación vial. #TomesusPrecauciones en #Chiapas se registra cierre parcial de circulación por #AccidenteVial",
      "link": "https://nitter.net/GN_Carreteras/status/2036496219531321609#m",
      "date": "2026-03-24T17:31:49+00:00"
    },
    {
      "id": "378e7ea13311",
      "account": "@GN_carreteras",
      "type": "accident",
      "highway": "?",
      "route_key": "unknown",
      "km": 43.0,
      "lat": 23.6345,
      "lon": -102.5528,
      "resolved": false,
      "text": "#TomesusPrecauciones en #Jalisco se registra cierre parcial de circulación por #AccidenteVial cerca del km 043+000, de la carretera Melaque – Puerto Vallarta, con dirección a Melaque, Jal. Atienda indicación vial. #TomesusPrecauciones en #Jalisco se registra cierre parcial de cir",
      "link": "https://nitter.net/GN_Carreteras/status/2036495395879104832#m",
      "date": "2026-03-24T17:28:33+00:00"
    },
    {
      "id": "575cb32356eb",
      "account": "@capufe",
      "type": "accident",
      "highway": "Cuernavaca–Acapulco",
      "route_key": "cuernavaca-acapulco",
      "km": 95.0,
      "lat": 18.271359,
      "lon": -99.519041,
      "resolved": true,
      "text": "🟠 CARGA VEHICULAR 🟠 Aut. Cuernavaca - Acapulco, km 95, dirección Acapulco. El accidente ha sido atendido. Sin embargo, en la zona se registra carga vehicular, derivado de las labores de mantenimiento del km 96. Maneja con precaución. 🟠 CARGA VEHICULAR 🟠 Aut. Cuernavaca - Acapulco",
      "link": "https://nitter.net/CAPUFE/status/2036488341567537388#m",
      "date": "2026-03-24T17:00:31+00:00"
    },
    {
      "id": "999eb807b4d3",
      "account": "@GN_carreteras",
      "type": "accident",
      "highway": "?",
      "route_key": "unknown",
      "km": 63.0,
      "lat": 23.6345,
      "lon": -102.5528,
      "resolved": false,
      "text": "#TomesusPrecauciones en #Puebla se registra cierre parcial de circulación por #AccidenteVial cerca del km 063+200, de la carretera San Hipólito - Xalapa Atienda indicación vial. #TomesusPrecauciones en #Puebla se registra cierre parcial de circulación por #AccidenteVial cerca del",
      "link": "https://nitter.net/GN_Carreteras/status/2036488268489892263#m",
      "date": "2026-03-24T17:00:13+00:00"
    },
    {
      "id": "c712e534bf01",
      "account": "@capufe",
      "type": "accident",
      "highway": "Cuernavaca–Acapulco",
      "route_key": "cuernavaca-acapulco",
      "km": 96.0,
      "lat": 18.253631,
      "lon": -99.522849,
      "resolved": true,
      "text": "🟢 RESTABLECIMIENTO DE CIRCULACIÓN 🟢 Autopista Cuernavaca - Acapulco, km 96, dirección Cuernavaca. El accidente ha sido atendido. Tramo opera de manera normal. Maneja con precaución. 🚌🚙🚗🏍️ 🟢 RESTABLECIMIENTO DE CIRCULACIÓN 🟢 Autopista Cuernavaca - Acapulco, km 96, dirección Cuerna",
      "link": "https://nitter.net/CAPUFE/status/2036486921762083022#m",
      "date": "2026-03-24T16:54:52+00:00"
    },
    {
      "id": "d2e4cd906a6f",
      "account": "@capufe",
      "type": "roadwork",
      "highway": "?",
      "route_key": "unknown",
      "km": 5.0,
      "lat": 23.6345,
      "lon": -102.5528,
      "resolved": false,
      "text": "🚧OBRAS Y LABORES DE MANTENIMIENTO🚧 Viaducto Elevado Tlalpan, km 5, dirección Cuernavaca. Reducción de carriles por labores de mantenimiento. Maneja con precaución. 🚧OBRAS Y LABORES DE MANTENIMIENTO🚧 Viaducto Elevado Tlalpan, km 5, dirección Cuernavaca. Reducción de carriles por l",
      "link": "https://nitter.net/CAPUFE/status/2036483133655437454#m",
      "date": "2026-03-24T16:39:49+00:00"
    },
    {
      "id": "44abe28439eb",
      "account": "@GN_carreteras",
      "type": "accident",
      "highway": "?",
      "route_key": "unknown",
      "km": 197.0,
      "lat": 23.6345,
      "lon": -102.5528,
      "resolved": false,
      "text": "#TomesusPrecauciones en #Veracruz se registra cierre parcial de circulación por #AccidenteVial cerca del km 197+200, de la carretera Posa Rica-Veracruz. Atienda indicación vial. #TomesusPrecauciones en #Veracruz se registra cierre parcial de circulación por #AccidenteVial cerca d",
      "link": "https://nitter.net/GN_Carreteras/status/2036483083113746720#m",
      "date": "2026-03-24T16:39:37+00:00"
    },
    {
      "id": "3a04229dd805",
      "account": "@GN_carreteras",
      "type": "accident",
      "highway": "Chih–Cd Juárez",
      "route_key": "chihuahua-juarez",
      "km": 263.0,
      "lat": 31.738,
      "lon": -106.487,
      "resolved": true,
      "text": "#TomesusPrecauciones en #Tamaulipas se registra cierre parcial de circulación por #AccidenteVial cerca del km 263+300, de la carretera Cd. Victoria - Matamoros. Atienda indicación vial. #TomesusPrecauciones en #Tamaulipas se registra cierre parcial de circulación por #AccidenteVi",
      "link": "https://nitter.net/GN_Carreteras/status/2036481613156978922#m",
      "date": "2026-03-24T16:33:47+00:00"
    },
    {
      "id": "adff4d6fed39",
      "account": "@GN_carreteras",
      "type": "accident",
      "highway": "?",
      "route_key": "unknown",
      "km": 128.0,
      "lat": 23.6345,
      "lon": -102.5528,
      "resolved": false,
      "text": "#TomesusPrecauciones en #Durango se registra cierre parcial de circulación por #AccidenteVial cerca del km 128+360, de la carretera Gómez Palacio - Jiménez. Atienda indicación vial. #TomesusPrecauciones en #Durango se registra cierre parcial de circulación por #AccidenteVial cerc",
      "link": "https://nitter.net/GN_Carreteras/status/2036479942477611327#m",
      "date": "2026-03-24T16:27:08+00:00"
    },
    {
      "id": "7774084c18c5",
      "account": "@GN_carreteras",
      "type": "accident",
      "highway": "?",
      "route_key": "unknown",
      "km": 9.0,
      "lat": 23.6345,
      "lon": -102.5528,
      "resolved": false,
      "text": "#TomesusPrecauciones en #Veracruz se registra cierre parcial de circulación por #AccidenteVial cerca del km 009+200, de la carretera Paso del Toro - Acayucan. Atienda indicación vial. #TomesusPrecauciones en #Veracruz se registra cierre parcial de circulación por #AccidenteVial c",
      "link": "https://nitter.net/GN_Carreteras/status/2036390367826731489#m",
      "date": "2026-03-24T10:31:12+00:00"
    },
    {
      "id": "5ab03a9c126a",
      "account": "@GN_carreteras",
      "type": "accident",
      "highway": "?",
      "route_key": "unknown",
      "km": 331.0,
      "lat": 23.6345,
      "lon": -102.5528,
      "resolved": false,
      "text": "#TomesusPrecauciones en #Coahuila se registra cierre parcial de circulación por #AccidenteVial cerca del km 331+800, de la carretera Puerto México - Ojo Caliente. Atienda indicación vial. #TomesusPrecauciones en #Coahuila se registra cierre parcial de circulación por #AccidenteVi",
      "link": "https://nitter.net/GN_Carreteras/status/2036288890001072315#m",
      "date": "2026-03-24T03:47:58+00:00"
    },
    {
      "id": "e0e8deae2b36",
      "account": "@GN_carreteras",
      "type": "blockade",
      "highway": "?",
      "route_key": "unknown",
      "km": 97.0,
      "lat": 23.6345,
      "lon": -102.5528,
      "resolved": false,
      "text": "#ViaLibre en #Veracruz tras presencia de personas cerca del Km 097+700 de la carretera San Hipólito - Xalapa. Maneje con precaución. #ViaLibre en #Veracruz tras presencia de personas cerca del Km 097+700 de la carretera San Hipólito - Xalapa. Maneje con precaución.",
      "link": "https://nitter.net/GN_Carreteras/status/2036254205862617371#m",
      "date": "2026-03-24T01:30:09+00:00"
    },
    {
      "id": "c3b9a557e6a7",
      "account": "@GN_carreteras",
      "type": "accident",
      "highway": "?",
      "route_key": "unknown",
      "km": 0.0,
      "lat": 23.6345,
      "lon": -102.5528,
      "resolved": false,
      "text": "#TomesusPrecauciones en #Guanajuato se registra cierre parcial de circulación por #AccidenteVial cerca del km 000+500, de la carretera Querétaro - León. Atienda indicación vial. #TomesusPrecauciones en #Guanajuato se registra cierre parcial de circulación por #AccidenteVial cerca",
      "link": "https://nitter.net/GN_Carreteras/status/2036237743739515068#m",
      "date": "2026-03-24T00:24:44+00:00"
    }
  ]
}